fortranmagic.py
fortran_magic-0.9.dist-info/LICENSE
fortran_magic-0.9.dist-info/METADATA
fortran_magic-0.9.dist-info/WHEEL
fortran_magic-0.9.dist-info/top_level.txt
fortran_magic-0.9.dist-info/RECORD
