Metadata-Version: 2.1
Name: fortran-magic
Version: 0.9
Summary: An extension for IPython that help to use Fortran in your interactive session.
Home-page: https://github.com/mgaitan/fortran_magic
Author: Martin Gaitan
Author-email: gaitan@gmail.com
License: BSD
Keywords: ipython notebook fortran f2py science
Classifier: Development Status :: 4 - Beta
Classifier: Environment :: Web Environment
Classifier: Framework :: IPython
Classifier: Intended Audience :: Science/Research
Classifier: License :: OSI Approved :: BSD License
Classifier: Operating System :: OS Independent
Classifier: Programming Language :: Python
Classifier: Programming Language :: Fortran
Classifier: Topic :: Software Development :: Libraries :: Python Modules
Classifier: Topic :: Scientific/Engineering
License-File: LICENSE
Requires-Dist: ipython
Requires-Dist: numpy
